{
  "kind": "feature_evidence_report",
  "features": [
    {
      "featureId": "feature-add-a-messages-ui-in-the-frontend-an-inbox-of-conversations-and-a-conversation-thread-screen-that-polls-for-new-messages-and-allows-sending-messages",
      "featureTitle": "Add a messages UI in the frontend: an inbox of conversations and a conversation thread screen that polls for new messages and allows sending messages.",
      "files": [
        "frontend/src/App.tsx",
        "frontend/src/components/Header.tsx",
        "frontend/src/hooks/useQueries.ts",
        "frontend/src/pages/MessagesInbox.tsx",
        "frontend/src/pages/MessagesThread.tsx"
      ],
      "components": [
        "core-infrastructure@1.0.2",
        "shadcn-ui@1.0.0",
        "build-template-react@1.0.0",
        "initial-app@1.0.0",
        "authorization@4.0.0",
        "blob-storage@4.0.0",
        "github-export-icp-cli@1.0.0"
      ],
      "testIds": [
        "REQ-2"
      ],
      "confidence": "high"
    },
    {
      "featureId": "feature-wire-the-existing-per-item-contact-action-to-open-the-in-app-chat-with-the-correct-listing-owner-creating-the-conversation-if-needed",
      "featureTitle": "Wire the existing per-item “Contact” action to open the in-app chat with the correct listing owner, creating the conversation if needed.",
      "files": [
        "frontend/src/components/ItemCard.tsx",
        "frontend/src/pages/BuySection.tsx",
        "frontend/src/pages/LostFoundSection.tsx",
        "frontend/src/pages/RentSection.tsx"
      ],
      "components": [
        "core-infrastructure@1.0.2",
        "shadcn-ui@1.0.0",
        "build-template-react@1.0.0",
        "initial-app@1.0.0",
        "authorization@4.0.0",
        "blob-storage@4.0.0",
        "github-export-icp-cli@1.0.0"
      ],
      "testIds": [
        "REQ-3"
      ],
      "confidence": "high"
    },
    {
      "featureId": "feature-update-the-existing-static-contact-page-to-clarify-it-is-for-support-feedback-and-add-a-clear-entry-point-to-the-new-in-app-messages-inbox-for-contacting-sellers-owners",
      "featureTitle": "Update the existing static Contact page to clarify it is for support/feedback, and add a clear entry point to the new in-app messages inbox for contacting sellers/owners.",
      "files": [
        "frontend/src/pages/Contact.tsx"
      ],
      "components": [
        "core-infrastructure@1.0.2",
        "shadcn-ui@1.0.0",
        "build-template-react@1.0.0",
        "initial-app@1.0.0",
        "authorization@4.0.0",
        "blob-storage@4.0.0",
        "github-export-icp-cli@1.0.0"
      ],
      "testIds": [
        "REQ-4"
      ],
      "confidence": "high"
    },
    {
      "featureId": "feature-apply-a-cohesive-visual-theme-across-the-new-chat-screens-so-they-match-the-marketplace-ui-using-a-distinct-style-that-is-consistent-throughout-the-messages-experience",
      "featureTitle": "Apply a cohesive visual theme across the new chat screens so they match the marketplace UI, using a distinct style that is consistent throughout the messages experience.",
      "files": [
        "frontend/src/index.css",
        "frontend/src/pages/MessagesInbox.tsx",
        "frontend/src/pages/MessagesThread.tsx"
      ],
      "components": [
        "core-infrastructure@1.0.2",
        "shadcn-ui@1.0.0",
        "build-template-react@1.0.0",
        "initial-app@1.0.0",
        "authorization@4.0.0",
        "blob-storage@4.0.0",
        "github-export-icp-cli@1.0.0"
      ],
      "testIds": [
        "REQ-5"
      ],
      "confidence": "high"
    }
  ]
}